{
  "db_name": "PostgreSQL",
  "query": "\n                UPDATE users SET username = $1\n                WHERE id = $2\n                RETURNING *\n            ",
  "describe": {
    "columns": [
      {
        "ordinal": 0,
        "name": "id",
        "type_info": "Int8"
      },
      {
        "ordinal": 1,
        "name": "username",
        "type_info": "Varchar"
      },
      {
        "ordinal": 2,
        "name": "email",
        "type_info": "Varchar"
      },
      {
        "ordinal": 3,
        "name": "password_hash",
        "type_info": "Varchar"
      },
      {
        "ordinal": 4,
        "name": "is_admin",
        "type_info": "Bool"
      },
      {
        "ordinal": 5,
        "name": "created_at",
        "type_info": "Timestamptz"
      }
    ],
    "parameters": {
      "Left": [
        "Varchar",
        "Int8"
      ]
    },
    "nullable": [
      false,
      false,
      false,
      false,
      false,
      false
    ]
  },
  "hash": "1908758da7c2e147cee73dca81caff0afc85a6902a132266e6cb4f2f04a5cb6c"
}
